calct/__init__.py
calct/__main__.py
calct/__version__.py
calct/_common.py
calct/_divmod.py
calct/_duration_parser.py
calct/duration.py
calct/main.py
calct/parser.py
calct-0.4.2.dist-info/LICENSE
calct-0.4.2.dist-info/METADATA
calct-0.4.2.dist-info/WHEEL
calct-0.4.2.dist-info/entry_points.txt
calct-0.4.2.dist-info/top_level.txt
calct-0.4.2.dist-info/RECORD
